cottontail/__init__.py
cottontail/rabbitmq_management.py
cottontail/utils.py
cottontail_offensive-0.8.4.data/scripts/cottontail
cottontail_offensive-0.8.4.dist-info/LICENSE
cottontail_offensive-0.8.4.dist-info/METADATA
cottontail_offensive-0.8.4.dist-info/WHEEL
cottontail_offensive-0.8.4.dist-info/top_level.txt
cottontail_offensive-0.8.4.dist-info/RECORD
