Metadata-Version: 2.1
Name: cottontail-offensive
Version: 0.8.4
Summary: Cottontail - A set of scripts to capture RabbitMQ messages.
Home-page: http://www.github.com/qkaiser/cottontail
Author: Quentin Kaiser
Author-email: kaiserquentin@gmail.com
License: BSD-3
Platform: UNKNOWN
Requires-Dist: coloredlogs
Requires-Dist: pika
Requires-Dist: requests
Requires-Dist: urllib3
Requires-Dist: verboselogs
